codesonor/__init__.py
codesonor/__main__.py
codesonor/ai_analyzer.py
codesonor/analyzer.py
codesonor/cache_manager.py
codesonor/cli.py
codesonor/comparator.py
codesonor/config.py
codesonor/dashboard.py
codesonor/exporter.py
codesonor/github_client.py
codesonor/language_insights.py
codesonor/language_stats.py
codesonor/llm_providers.py
codesonor/quality_scorer.py
codesonor/rules_engine.py
codesonor/watcher.py
codesonor-0.4.1.dist-info/licenses/LICENSE
codesonor-0.4.1.dist-info/METADATA
codesonor-0.4.1.dist-info/WHEEL
codesonor-0.4.1.dist-info/entry_points.txt
codesonor-0.4.1.dist-info/top_level.txt
codesonor-0.4.1.dist-info/RECORD
