Metadata-Version: 2.4
Name: codesonor
Version: 0.4.1
Summary: AI-Powered GitHub Repository Analyzer - 8 LLM providers (Gemini, OpenAI, Claude, Mistral, Groq, OpenRouter, xAI, Ollama), caching, quality scoring, exports, watch mode, dashboard
Author: Farhan Mir
License: MIT
Project-URL: Homepage, https://github.com/farhanmir/CodeSonor
Project-URL: Repository, https://github.com/farhanmir/CodeSonor
Project-URL: Bug Tracker, https://github.com/farhanmir/CodeSonor/issues
Keywords: github,repository,analyzer,ai,code-analysis,gemini,cli,quality,caching
Classifier: Development Status :: 4 - Beta
Classifier: Intended Audience :: Developers
Classifier: License :: OSI Approved :: MIT License
Classifier: Programming Language :: Python :: 3
Classifier: Programming Language :: Python :: 3.9
Classifier: Programming Language :: Python :: 3.10
Classifier: Programming Language :: Python :: 3.11
Classifier: Programming Language :: Python :: 3.12
Classifier: Topic :: Software Development :: Libraries :: Python Modules
Classifier: Topic :: Software Development :: Version Control :: Git
Requires-Python: >=3.9
License-File: LICENSE
Requires-Dist: requests>=2.31.0
Requires-Dist: google-generativeai>=0.3.2
Requires-Dist: python-dotenv>=1.0.0
Requires-Dist: click>=8.1.0
Requires-Dist: rich>=13.0.0
Requires-Dist: pyyaml>=6.0.0
Provides-Extra: gemini
Requires-Dist: google-generativeai>=0.3.0; extra == "gemini"
Provides-Extra: openai
Requires-Dist: openai>=1.0.0; extra == "openai"
Provides-Extra: anthropic
Requires-Dist: anthropic>=0.18.0; extra == "anthropic"
Provides-Extra: mistral
Requires-Dist: mistralai>=0.1.0; extra == "mistral"
Provides-Extra: groq
Requires-Dist: groq>=0.4.0; extra == "groq"
Provides-Extra: all-llm
Requires-Dist: google-generativeai>=0.3.0; extra == "all-llm"
Requires-Dist: openai>=1.0.0; extra == "all-llm"
Requires-Dist: anthropic>=0.18.0; extra == "all-llm"
Requires-Dist: mistralai>=0.1.0; extra == "all-llm"
Requires-Dist: groq>=0.4.0; extra == "all-llm"
Provides-Extra: dev
Requires-Dist: pytest>=7.0.0; extra == "dev"
Requires-Dist: black>=23.0.0; extra == "dev"
Requires-Dist: flake8>=6.0.0; extra == "dev"
Requires-Dist: mypy>=1.0.0; extra == "dev"
Provides-Extra: web
Requires-Dist: Flask>=3.0.0; extra == "web"
Requires-Dist: Flask-CORS>=4.0.0; extra == "web"
Dynamic: license-file
